clairview/__init__.py
clairview/client.py
clairview/consumer.py
clairview/exception_capture.py
clairview/exception_utils.py
clairview/feature_flags.py
clairview/poller.py
clairview/py.typed
clairview/request.py
clairview/utils.py
clairview/version.py
clairview/exception_integrations/__init__.py
clairview/exception_integrations/django.py
clairview/sentry/__init__.py
clairview/sentry/clairview_integration.py
clairview/sentry/django.py
clairview/test/__init__.py
clairview/test/test_client.py
clairview/test/test_consumer.py
clairview/test/test_exception_capture.py
clairview/test/test_feature_flags.py
clairview/test/test_module.py
clairview/test/test_request.py
clairview/test/test_utils.py
clairview-3.7.0.dist-info/LICENSE
clairview-3.7.0.dist-info/METADATA
clairview-3.7.0.dist-info/WHEEL
clairview-3.7.0.dist-info/top_level.txt
clairview-3.7.0.dist-info/RECORD
